bwslib/__init__.py
bwslib/bws_auth.py
bwslib/sseclient.py
lineage_bwslib-0.0.3.dist-info/METADATA
lineage_bwslib-0.0.3.dist-info/WHEEL
lineage_bwslib-0.0.3.dist-info/top_level.txt
lineage_bwslib-0.0.3.dist-info/RECORD
