Metadata-Version: 2.1
Name: lineage-bwslib
Version: 0.0.3
Summary: BWS auth lib package
Classifier: Programming Language :: Python
Classifier: License :: OSI Approved :: MIT License
Classifier: Operating System :: OS Independent
Requires-Dist: PyJWT
Requires-Dist: requests
Requires-Dist: retrying
Requires-Dist: urllib3
